<!--
    <USER>
        NAME
        EMAIL
        PASSWORD
    </USER>
-->


<USER>
    <NAME>Smit Desai</NAME>
    <EMAIL>smitdesai1010@gmail.com</EMAIL>
    <PASSWORD>smit1010</PASSWORD>
</USER>

<USER>
    <NAME>Alexa Translations</NAME>
    <EMAIL>smitdesai1010@gmail.com</EMAIL>
    <PASSWORD>asd</PASSWORD>
</USER>

<USER>
	<NAME>Dovetail</NAME>
	<EMAIL>matrox#</EMAIL>
	<PASSWORD>asd</PASSWORD>
</USER>

<USER>
	<NAME>Smit Desai</NAME>
	<EMAIL>smitdesai1010gmail.com</EMAIL>
	<PASSWORD>ert</PASSWORD>
</USER>

<USER>
	<NAME>Smit Desai</NAME>
	<EMAIL>smitdesai1010@gmail.com</EMAIL>
	<PASSWORD>asd</PASSWORD>
</USER>